{
  "id": "646b7187b50b2a93b1ae3d45",
  "title": "Dataset 646b7187b50b2a93b1ae3d45",
  "slug": "646b7187b50b2a93b1ae3d45",
  "organization": "Inconnu",
  "organizationId": "",
  "url": "https://www.data.gouv.fr/fr/datasets/646b7187b50b2a93b1ae3d45/",
  "totalVisits": 98956,
  "totalDownloads": 0,
  "monthlyStats": [
    {
      "month": "2023-04",
      "visits": 0,
      "downloads": 0
    },
    {
      "month": "2023-05",
      "visits": 0,
      "downloads": 0
    },
    {
      "month": "2023-06",
      "visits": 0,
      "downloads": 0
    },
    {
      "month": "2023-07",
      "visits": 0,
      "downloads": 0
    },
    {
      "month": "2023-08",
      "visits": 0,
      "downloads": 0
    },
    {
      "month": "2023-09",
      "visits": 0,
      "downloads": 0
    },
    {
      "month": "2023-10",
      "visits": 0,
      "downloads": 0
    },
    {
      "month": "2023-11",
      "visits": 0,
      "downloads": 0
    },
    {
      "month": "2023-12",
      "visits": 0,
      "downloads": 0
    },
    {
      "month": "2024-01",
      "visits": 0,
      "downloads": 0
    },
    {
      "month": "2024-02",
      "visits": 0,
      "downloads": 0
    },
    {
      "month": "2024-03",
      "visits": 0,
      "downloads": 0
    },
    {
      "month": "2024-04",
      "visits": 0,
      "downloads": 0
    },
    {
      "month": "2024-05",
      "visits": 0,
      "downloads": 0
    },
    {
      "month": "2024-06",
      "visits": 0,
      "downloads": 0
    },
    {
      "month": "2024-07",
      "visits": 0,
      "downloads": 0
    },
    {
      "month": "2024-08",
      "visits": 0,
      "downloads": 0
    },
    {
      "month": "2024-09",
      "visits": 0,
      "downloads": 0
    },
    {
      "month": "2024-10",
      "visits": 0,
      "downloads": 0
    },
    {
      "month": "2024-11",
      "visits": 0,
      "downloads": 0
    },
    {
      "month": "2024-12",
      "visits": 0,
      "downloads": 0
    },
    {
      "month": "2025-01",
      "visits": 0,
      "downloads": 0
    },
    {
      "month": "2025-02",
      "visits": 1448,
      "downloads": 0
    },
    {
      "month": "2025-03",
      "visits": 2393,
      "downloads": 0
    },
    {
      "month": "2025-04",
      "visits": 6776,
      "downloads": 0
    },
    {
      "month": "2025-05",
      "visits": 15573,
      "downloads": 0
    },
    {
      "month": "2025-06",
      "visits": 13177,
      "downloads": 0
    },
    {
      "month": "2025-07",
      "visits": 11113,
      "downloads": 0
    },
    {
      "month": "2025-08",
      "visits": 9404,
      "downloads": 0
    },
    {
      "month": "2025-09",
      "visits": 11667,
      "downloads": 0
    },
    {
      "month": "2025-10",
      "visits": 14118,
      "downloads": 0
    },
    {
      "month": "2025-11",
      "visits": 12586,
      "downloads": 0
    },
    {
      "month": "2025-12",
      "visits": 701,
      "downloads": 0
    }
  ],
  "firstMonth": "2023-04",
  "lastMonth": "2025-12"
}